mcmc_estimator/__init__.py
mcmc_estimator/mcmc_param_est.py
mcmc_estimator-0.0.2.dist-info/METADATA
mcmc_estimator-0.0.2.dist-info/WHEEL
mcmc_estimator-0.0.2.dist-info/top_level.txt
mcmc_estimator-0.0.2.dist-info/RECORD
