Metadata-Version: 2.1
Name: mcmc-estimator
Version: 0.0.2
Summary: Estimates a function's parameters using Metropolis-Hastings to fit data.
Home-page: https://github.com/nickgerend/mcmc-estimator
Author: Nick Gerend
Author-email: nickgerend@gmail.com
License: MIT
Classifier: Programming Language :: Python :: 3.9
Classifier: License :: OSI Approved :: MIT License
Requires-Dist: numpy
Requires-Dist: matplotlib
